{
  "theme": "base",
  "pageTitle": "Steven Ruddell - CV",
  "showMenu": true,
  "profile": {
    "firstname": "Steven",
    "lastname": "Ruddell",
    "brief": "Instructor, Political Scientist, and Football Watcher.",
    "image": "./static/profile.jpg",
    "details": [
      {
        "title": "Location",
        "value": "Charlottesville, VA",
        "icon": "fa-globe"
      },
      {
        "title": "Hometown",
        "value": "Charlottesville",
        "icon": "fa-map-signs"
      }
    ],
    "external": [
      {
        "title": "LinkedIn",
        "value": "http://linkedin.com/in/stevenruddell",
        "icon": "fa-linkedin"
      },
      {
        "title": "Github",
        "value": "http://github.com/steveruddell",
        "icon": "fa-github"
      },
      {
        "title": "Twitter",
        "value": "https://twitter.com/steveruddell",
        "icon": "fa-twitter"
      }
    ]
  },
  "biography": {
    "display": true,
    "text": "Web application developer, with full-stack experience, strong organizational skills and extensive project management and leadership experience. Creative and motivated analytical thinker, able to propose practical solutions to abstract problem sets. Extensive Information Technology knowledge and experience.",
    "headline": "About Me"
  },
  "skills": {
    "display": true,
    "displayProgress": true,
    "items": [
    {
      "name": "Javascript",
      "description": "Self-taught. Constructed several applications, especially with Vue.",
      "value": 15,
      "icon": "fa-bug"
    },
    {
      "name": ".NET (C#, VB)",
      "description": "Developed various web based applications.",
      "value": 80,
      "icon": "fa-coffee"
    },
    {
      "name": "Swift",
      "description": "Learning alongside my 8 yr old.",
      "value": 15,
      "icon": "fa-apple"
    },
    {
      "name": "Python",
      "description": "Learning alongside my 8 yr old.",
      "value": 15,
      "icon": "fa-firefox"
    }
  ]},
  "languages": {
    "display": true,
    "items": [
    {
      "name": "English",
      "description": "Native Speaker",
      "value": 90,
      "icon": "US"
    },
    {
      "name": "Russian",
      "description": "Visited in high school; lived for a semester abroad. University education & self-taught beyond.",
      "value": 85,
      "icon": "RU"
    }
  ]},
  "employment": {
    "display": true,
    "items": [
    {
      "name": "Silverchair Information Systems",
      "end": "present",
      "start": "2011",
      "location": "Charlottesville, VA",
      "position": "Developer, DevOps Automation Engineer",
      "description": "Will serve as instructor for three units of Integrated English at varying levels. Additionally, will instruct the Academic Presentations course.",
      "website": "http://www.silverchair.com"
    },
    {
      "name": "Kmart",
      "start": "2017-01-31",
      "end": "2017-09-04",
      "location": "Columbia, Pennsylvania",
      "position": "Customer Service Representative",
      "description": "Acted as primary customer service representative in the store. Responsible for customer needs such as: returns, exchanges, check cashing, bill payments, and wire transfers. Coordinated with management for handling of cashiers and floor staff, setting up merchandise displays, and announcing and executing in-store promotions.",
      "website": "http://kmart.com"
    }
  ]},
  "education": {
    "display": true,
    "items": [
    {
      "name": "James Madison University",
      "end": "1999-05-14",
      "start": "1995-08-01",
      "location": "Harrisonburg, VA",
      "degree": "BS",
      "major": "Computer Science",
      "website": "http://jmu.edu",
      "description": ""
    },
    {
      "name": "James Madison University",
      "end": "1999-05-14",
      "start": "1995-08-01",
      "location": "Harrisonburg, VA",
      "degree": "BA",
      "major": "Russian Language",
      "website": "http://jmu.edu",
      "description": ""
    },
    {
      "name": "Covenant Theological Seminary",
      "end": "2007-05-01",
      "start": "2003-06-01",
      "location": "St Louis, MO",
      "degree": "MDiv",
      "website": "http://covenantseminary.edu",
      "description": ""
    }
  ]}
}
